tests/integration/__init__.py
tests/integration/test_dags.py
tests/operators/__init__.py
tests/operators/test_operators_cypress.py
tests/operators/test_operators_io.py
tests/operators/test_operators_qt.py
ytsaurus_airflow_provider/__init__.py
ytsaurus_airflow_provider/example_dags/__init__.py
ytsaurus_airflow_provider/example_dags/ytsaurus_cypress_example.py
ytsaurus_airflow_provider/example_dags/ytsaurus_io_example.py
ytsaurus_airflow_provider/example_dags/ytsaurus_qt_example.py
ytsaurus_airflow_provider/hooks/__init__.py
ytsaurus_airflow_provider/hooks/ytsaurus.py
ytsaurus_airflow_provider/operators/__init__.py
ytsaurus_airflow_provider/operators/ytsaurus_cypress.py
ytsaurus_airflow_provider/operators/ytsaurus_io.py
ytsaurus_airflow_provider/operators/ytsaurus_qt.py
ytsaurus_airflow_provider-0.1.1.dist-info/LICENSE
ytsaurus_airflow_provider-0.1.1.dist-info/METADATA
ytsaurus_airflow_provider-0.1.1.dist-info/WHEEL
ytsaurus_airflow_provider-0.1.1.dist-info/entry_points.txt
ytsaurus_airflow_provider-0.1.1.dist-info/top_level.txt
ytsaurus_airflow_provider-0.1.1.dist-info/RECORD
