Metadata-Version: 2.1
Name: ytsaurus-airflow-provider
Version: 0.1.1
Summary: YTsaurus Apache Airflow provider.
Author-email: YTsaurus <ilyaibraev@ytsaurus.tech>
License: Apache License 2.0
Project-URL: Homepage, https://ytsaurus.tech/
Project-URL: Source, https://github.com/ytsaurus/ytsaurus-airflow-provider/
Classifier: Framework :: Apache Airflow
Classifier: Framework :: Apache Airflow :: Provider
Classifier: Programming Language :: Python :: 3.8
Classifier: Programming Language :: Python :: 3.9
Classifier: Programming Language :: Python :: 3.10
Classifier: Programming Language :: Python :: 3.11
Classifier: Programming Language :: Python :: 3.12
Requires-Python: >=3.8
License-File: LICENSE
Requires-Dist: apache-airflow>=2.9.0
Requires-Dist: ytsaurus-client>=0.13.23
Requires-Dist: ytsaurus-yson>=0.4.3
Requires-Dist: apache-airflow-providers-amazon[s3fs]>=3.0.0
Requires-Dist: s3fs<=2024.10.0
